paddle_lpips/__init__.py
paddle_lpips/lpips.py
paddle_lpips/pretrained_networks.py
paddle_lpips/trainer.py
paddle_lpips/models/__init__.py
paddle_lpips/models/alexnet.py
paddle_lpips/models/squeezenet.py
paddle_lpips/models/vgg.py
paddle_lpips/weights/v0.0/alex.pdparams
paddle_lpips/weights/v0.0/squeeze.pdparams
paddle_lpips/weights/v0.0/vgg.pdparams
paddle_lpips/weights/v0.1/alex.pdparams
paddle_lpips/weights/v0.1/squeeze.pdparams
paddle_lpips/weights/v0.1/vgg.pdparams
paddle_lpips-0.1.2.0.dist-info/LICENSE
paddle_lpips-0.1.2.0.dist-info/METADATA
paddle_lpips-0.1.2.0.dist-info/WHEEL
paddle_lpips-0.1.2.0.dist-info/top_level.txt
paddle_lpips-0.1.2.0.dist-info/RECORD
