Metadata-Version: 2.1
Name: paddle-lpips
Version: 0.1.2.0
Summary: PaddlePaddle version of LPIPS Similarity metric
Home-page: https://github.com/AgentMaker/Paddle-PerceptualSimilarity
Author: AgentMaker
Author-email: agentmaker@163.com
License: UNKNOWN
Platform: UNKNOWN
Classifier: Programming Language :: Python :: 3
Classifier: License :: OSI Approved :: BSD License
Classifier: Operating System :: OS Independent
